README.md
setup.py
toka/__init__.py
toka/toka.py
toka/utils.py
tokaafrika.egg-info/PKG-INFO
tokaafrika.egg-info/SOURCES.txt
tokaafrika.egg-info/dependency_links.txt
tokaafrika.egg-info/not-zip-safe
tokaafrika.egg-info/top_level.txt